{
  "sections": {
    "hero_blog": {
      "type": "hero",
      "blocks": {
        "eyebrow": {
          "type": "text",
          "settings": {
            "text": "<p>Baidada Édition</p>",
            "type_preset": "body",
            "font_size": "0.75rem",
            "letter_spacing": "0.2em",
            "case": "uppercase",
            "alignment": "center",
            "color": "var(--color-foreground)"
          }
        },
        "titre": {
          "type": "text",
          "settings": {
            "text": "<h1>Réflexions &amp; Intelligence</h1>",
            "type_preset": "h1",
            "alignment": "center",
            "color": "var(--color-foreground-heading)"
          }
        },
        "sous_titre": {
          "type": "text",
          "settings": {
            "text": "<p>Psychologie, prévention, développement de soi — pour ceux qui veulent voir avant la chute.</p>",
            "type_preset": "body",
            "font_size": "1.1rem",
            "alignment": "center",
            "color": "var(--color-foreground)"
          }
        }
      },
      "block_order": ["eyebrow", "titre", "sous_titre"],
      "settings": {
        "color_scheme": "scheme-5",
        "content_position_desktop": "center",
        "content_alignment_desktop": "center",
        "min_height_desktop": 40,
        "padding-block-start": 80,
        "padding-block-end": 80
      }
    },
    "marquee_categories": {
      "type": "marquee",
      "blocks": {
        "c1": { "type": "text", "settings": { "text": "Psychologie" } },
        "c2": { "type": "text", "settings": { "text": "Réflexions" } },
        "c3": { "type": "text", "settings": { "text": "Maximes" } },
        "c4": { "type": "text", "settings": { "text": "Développement personnel" } },
        "c5": { "type": "text", "settings": { "text": "Avant la Chute" } },
        "c6": { "type": "text", "settings": { "text": "Intelligence préventive" } }
      },
      "block_order": ["c1", "c2", "c3", "c4", "c5", "c6"],
      "settings": {
        "color_scheme": "scheme-2",
        "movement_direction": "left",
        "padding-block-start": 16,
        "padding-block-end": 16
      }
    },
    "main": {
      "type": "main-blog",
      "blocks": {
        "title": {
          "type": "text",
          "name": "Title",
          "settings": {
            "text": "",
            "width": "fit-content",
            "max_width": "narrow",
            "alignment": "left",
            "type_preset": "h2",
            "font": "var(--font-primary--family)",
            "font_size": "",
            "line_height": "normal",
            "letter_spacing": "normal",
            "case": "none",
            "wrap": "pretty",
            "color": "",
            "background": false,
            "background_color": "#00000026",
            "corner_radius": 0,
            "padding-block-start": 0,
            "padding-block-end": 0,
            "padding-inline-start": 0,
            "padding-inline-end": 0
          },
          "blocks": {}
        },
        "static-blog-post-card": {
          "type": "_blog-post-card",
          "static": true,
          "settings": {
            "alignment": "left"
          },
          "blocks": {
            "heading": {
              "type": "_heading",
              "name": "Title",
              "static": true,
              "settings": {
                "type_preset": "h4",
                "font": "var(--font-primary--family)",
                "font_size": "",
                "line_height": "normal",
                "letter_spacing": "normal",
                "case": "none",
                "wrap": "pretty",
                "color": "",
                "text": "",
                "read_only": true,
                "alignment": "left",
                "show_alignment": false,
                "padding-block-start": 0,
                "padding-block-end": 10,
                "padding-inline-start": 0,
                "padding-inline-end": 0
              },
              "blocks": {}
            },
            "blog-post-details": {
              "type": "_blog-post-info-text",
              "name": "Details",
              "static": true,
              "settings": {
                "show_date": true,
                "show_author": true,
                "type_preset": "",
                "alignment": "left",
                "show_alignment": false,
                "padding-block-start": 0,
                "padding-block-end": 0
              },
              "blocks": {}
            },
            "image": {
              "type": "_blog-post-image",
              "static": true,
              "settings": {
                "height": "large",
                "border": "none",
                "border_width": 1,
                "border_opacity": 100,
                "border_radius": 0
              },
              "blocks": {}
            }
          },
          "block_order": []
        }
      },
      "block_order": [
        "title"
      ],
      "settings": {
        "color_scheme": "scheme-1",
        "padding-block-start": 0,
        "padding-block-end": 48
      }
    },
    "newsletter_blog": {
      "type": "hero",
      "blocks": {
        "titre": {
          "type": "text",
          "settings": {
            "text": "<h2>Ne manquez aucun article</h2>",
            "type_preset": "h2",
            "alignment": "center",
            "color": "var(--color-foreground-heading)"
          }
        },
        "desc": {
          "type": "text",
          "settings": {
            "text": "<p>Rejoignez la communauté Baidada Édition et recevez les nouvelles réflexions directement dans votre boîte.</p>",
            "type_preset": "body",
            "alignment": "center",
            "color": "var(--color-foreground)"
          }
        },
        "form": {
          "type": "email-signup",
          "settings": {}
        }
      },
      "block_order": ["titre", "desc", "form"],
      "settings": {
        "color_scheme": "scheme-5",
        "content_position_desktop": "center",
        "content_alignment_desktop": "center",
        "min_height_desktop": 20,
        "padding-block-start": 80,
        "padding-block-end": 80
      }
    }
  },
  "order": [
    "hero_blog",
    "marquee_categories",
    "main",
    "newsletter_blog"
  ]
}
